{
    "table": {
        "title": "## Table of Contents",
        "content": "* [Installation](#installation)\r\n* [Usage](#usage)\r\n* [License](#license)\r\n* [Contributing](#contributing)\r\n* [Tests](#tests)\r\n* [Credits](#credits)\r\n* [Questions](#questions)"
    },
    "description": {
        "title": "## Description",
        "content": ""
    },
    "installation": {
        "title": "## Installation",
        "content": ""
    },
    "usage": {
        "title": "## Usage",
        "content": ""
    },
    "contributing": {
        "title": "## Contributing",
        "content": ""
    },
    "tests": {
        "title": "## Tests",
        "content": ""
    }
}